odoo9_addon_web_tree_dynamic_colored_field-9.0.2.0.0.99.dev3-py2.7-nspkg.pth
odoo9_addon_web_tree_dynamic_colored_field-9.0.2.0.0.99.dev3.dist-info/DESCRIPTION.rst
odoo9_addon_web_tree_dynamic_colored_field-9.0.2.0.0.99.dev3.dist-info/METADATA
odoo9_addon_web_tree_dynamic_colored_field-9.0.2.0.0.99.dev3.dist-info/RECORD
odoo9_addon_web_tree_dynamic_colored_field-9.0.2.0.0.99.dev3.dist-info/WHEEL
odoo9_addon_web_tree_dynamic_colored_field-9.0.2.0.0.99.dev3.dist-info/metadata.json
odoo9_addon_web_tree_dynamic_colored_field-9.0.2.0.0.99.dev3.dist-info/namespace_packages.txt
odoo9_addon_web_tree_dynamic_colored_field-9.0.2.0.0.99.dev3.dist-info/top_level.txt
odoo_addons/web_tree_dynamic_colored_field/README.rst
odoo_addons/web_tree_dynamic_colored_field/__init__.py
odoo_addons/web_tree_dynamic_colored_field/__openerp__.py
odoo_addons/web_tree_dynamic_colored_field/demo/res_users.xml
odoo_addons/web_tree_dynamic_colored_field/i18n/de.po
odoo_addons/web_tree_dynamic_colored_field/i18n/es.po
odoo_addons/web_tree_dynamic_colored_field/i18n/fi.po
odoo_addons/web_tree_dynamic_colored_field/i18n/pt_BR.po
odoo_addons/web_tree_dynamic_colored_field/i18n/sl.po
odoo_addons/web_tree_dynamic_colored_field/static/description/icon.png
odoo_addons/web_tree_dynamic_colored_field/static/src/js/web_tree_dynamic_colored_field.js
odoo_addons/web_tree_dynamic_colored_field/static/src/xml/web_tree_dynamic_colored_field.xml
odoo_addons/web_tree_dynamic_colored_field/views/web_tree_dynamic_colored_field.xml
