Metadata-Version: 2.0
Name: odoo9-addon-web-tree-dynamic-colored-field
Version: 9.0.2.0.0.99.dev3
Summary: Allows you to dynamically color fields on tree views
Home-page: https://github.com/OCA/web
Author: Camptocamp,Therp BV,Odoo Community Association (OCA)
Author-email: support@odoo-community.org
License: AGPL-3
Platform: UNKNOWN
Classifier: Programming Language :: Python
Classifier: Framework :: Odoo
Classifier: License :: OSI Approved :: GNU Affero General Public License v3
Requires-Python: ~=2.7
Requires-Dist: odoo (<9.1a,>=9.0a)
